track_bump/__init__.py
track_bump/__main__.py
track_bump/bump.py
track_bump/config.py
track_bump/env.py
track_bump/logs.py
track_bump/tags.py
track_bump/utils.py
track_bump-0.10.0.dist-info/METADATA
track_bump-0.10.0.dist-info/WHEEL
track_bump-0.10.0.dist-info/entry_points.txt
track_bump-0.10.0.dist-info/RECORD
