Metadata-Version: 2.4
Name: track-bump
Version: 0.10.0
Summary: Utility library for bumping version numbers in project files
Author-email: Julien Brayere <julien.brayere@tracktor.com>
Requires-Python: >=3.12
Requires-Dist: piou>=0.14.2
